eiki/__init__.py
eiki/commands/__init__.py
eiki/config/__init__.py
eiki/config/conf.py
eiki/config/conf_fields.py
eiki/dev-service/__init__.py
eiki/dev-service/config.py
eiki/py.typed
eiki-0.1.0.dist-info/WHEEL
eiki-0.1.0.dist-info/METADATA
eiki-0.1.0.dist-info/RECORD
