Metadata-Version: 2.3
Name: eiki
Version: 0.1.0
Summary: Add your description here
Author: Eik Dahms
Author-email: Eik Dahms <eik.dahms@gmail.com>
Requires-Dist: pydantic>=2.12.0
Requires-Dist: pytest>=8.4.2
Requires-Python: >=3.10
